revolver_api/__init__.py
revolver_api/api.py
revolver_api/config/__init__.py
revolver_api/model.py
revolver_api/response.py
revolver_api/route.py
revolver_api/utils/get_request_args.py
revolver_api-0.1.3.dist-info/METADATA
revolver_api-0.1.3.dist-info/WHEEL
revolver_api-0.1.3.dist-info/RECORD
