Metadata-Version: 2.1
Name: revolver-api
Version: 0.1.3
Summary: 
Author: suke
Author-email: suke971219@gmail.com
Requires-Python: >=3.11,<4.0
Classifier: Programming Language :: Python :: 3
Classifier: Programming Language :: Python :: 3.11
Classifier: Programming Language :: Python :: 3.12
Requires-Dist: django (>=5.0.1,<6.0.0)
